irbasis_util/__init__.py
irbasis_util/four_point.py
irbasis_util/four_point_ph_view.py
irbasis_util/internal.py
irbasis_util/lsqr.py
irbasis_util/regression.py
irbasis_util/tensor_regression.py
irbasis_util/tensor_regression_mps.py
irbasis_util/three_point.py
irbasis_util/two_point_basis.py
irbasis_utility-0.9.dist-info/METADATA
irbasis_utility-0.9.dist-info/RECORD
irbasis_utility-0.9.dist-info/WHEEL
irbasis_utility-0.9.dist-info/top_level.txt
