Metadata-Version: 2.1
Name: irbasis-utility
Version: 0.9
Summary: Utility python libraries for irbasis
Home-page: https://github.com/shinaoka/irbasis_utility
Author: Hiroshi Shinaoka, Markus Wallerberger, Dominique Geffroy
Author-email: h.shinaoka@gmail.com
License: UNKNOWN
Keywords: quantum many-body theory
Platform: UNKNOWN
Classifier: Development Status :: 3 - Alpha
Classifier: Intended Audience :: Developers
Classifier: Topic :: Scientific/Engineering
Classifier: License :: OSI Approved :: MIT License
Classifier: Programming Language :: Python :: 2
Classifier: Programming Language :: Python :: 2.7
Classifier: Programming Language :: Python :: 3
Classifier: Programming Language :: Python :: 3.4
Classifier: Programming Language :: Python :: 3.5
Classifier: Programming Language :: Python :: 3.6
Requires-Dist: scipy
Requires-Dist: irbasis (>=1.0.4)
